livekit/plugins/turn_detection/__init__.py
livekit/plugins/turn_detection/constants.py
livekit/plugins/turn_detection/log.py
livekit/plugins/turn_detection/model.py
livekit/plugins/turn_detection/py.typed
livekit/plugins/turn_detection/version.py
livekit/plugins/turn_detection/onnx_model/added_tokens.json
livekit/plugins/turn_detection/onnx_model/config.json
livekit/plugins/turn_detection/onnx_model/model_quantized.onnx
livekit/plugins/turn_detection/onnx_model/ort_config.json
livekit/plugins/turn_detection/onnx_model/special_tokens_map.json
livekit/plugins/turn_detection/onnx_model/spm.model
livekit_plugins_turn_detection-1.0.1.dist-info/METADATA
livekit_plugins_turn_detection-1.0.1.dist-info/WHEEL
livekit_plugins_turn_detection-1.0.1.dist-info/RECORD
