Metadata-Version: 2.4
Name: livekit-plugins-turn-detection
Version: 1.0.1
Summary: End of utterance detection for LiveKit Agents
Project-URL: Documentation, https://docs.livekit.io
Project-URL: Website, https://livekit.io/
Project-URL: Source, https://github.com/livekit/agents
Author: ggroup
License-Expression: Apache-2.0
Keywords: agent,ai,audio,livekit
Classifier: Development Status :: 4 - Beta
Classifier: Intended Audience :: Developers
Classifier: Topic :: Communications :: Conferencing
Classifier: Topic :: Multimedia :: Sound/Audio
Classifier: Topic :: Multimedia :: Video
Classifier: Topic :: Scientific/Engineering :: Artificial Intelligence
Requires-Python: >=3.11
Requires-Dist: jinja2
Requires-Dist: livekit-agents>=1.2.18
Requires-Dist: numpy>=1.27
Requires-Dist: onnxruntime>=1.18
Requires-Dist: python-dotenv>=1.2.1
Requires-Dist: sentencepiece>=0.2.1
Requires-Dist: transformers>=4.47.1
